kaka/__init__.py
kaka/app.py
kaka/combinations.py
kaka/errors.py
kaka/middlewares.py
kaka/render.py
kaka/request.py
kaka/response.py
kaka/restful.py
kaka/routing.py
kaka/utils.py
KaKa-0.1.1.dist-info/LICENSE
KaKa-0.1.1.dist-info/METADATA
KaKa-0.1.1.dist-info/WHEEL
KaKa-0.1.1.dist-info/top_level.txt
KaKa-0.1.1.dist-info/RECORD
