Metadata-Version: 2.1
Name: KaKa
Version: 0.1.1
Summary: A simple and easy-to-use web framework
Home-page: https://github.com/zlw10100/kaka/
Author: zouliwei
Author-email: 330494152@qq.com
License: BSD
Keywords: pip,web,framework,wsgi,restful
Platform: any
Classifier: Programming Language :: Python :: 3
Classifier: License :: OSI Approved :: BSD License
Classifier: Operating System :: OS Independent
Requires-Dist: Werkzeug (>=0.14.1)
Requires-Dist: jinja2 (>=2.10)
